mikrotik_upgrade/__init__.py
mikrotik_upgrade/upgrade.py
mikrotik_upgrade-0.1.1.dist-info/METADATA
mikrotik_upgrade-0.1.1.dist-info/WHEEL
mikrotik_upgrade-0.1.1.dist-info/entry_points.txt
mikrotik_upgrade-0.1.1.dist-info/top_level.txt
mikrotik_upgrade-0.1.1.dist-info/RECORD
