Metadata-Version: 2.4
Name: mikrotik-upgrade
Version: 0.1.1
Summary: A minmal tool for mass upgrade Mikrotik routers
Classifier: Programming Language :: Python :: 3
Classifier: License :: OSI Approved :: MIT License
Classifier: Operating System :: OS Independent
Requires-Python: >=3.12
Requires-Dist: click>=8.3.1
Requires-Dist: paramiko>=4.0.0
Requires-Dist: pyyaml>=6.0.3
